{"cameraMode":{"drawMode":0,"name":"Shaded","section":"Shading Mode"},"sceneLighting":true,"audioPlay":false,"sceneViewState":{"m_AlwaysRefresh":false,"showFog":true,"showSkybox":true,"showFlares":true,"showImageEffects":true,"showParticleSystems":true,"showVisualEffectGraphs":true,"m_FxEnabled":true},"in2DMode":false,"pivot":{"x":16.516754150390626,"y":116.29228973388672,"z":3.924531936645508},"rotation":{"x":-0.06095457822084427,"y":0.4932200312614441,"z":0.03468870744109154,"w":0.8670797944068909},"size":11.520614624023438,"orthographic":false}